is_pku/__init__.py
is_pku/__main__.py
is_pku-0.1.2.dist-info/licenses/LICENSE
is_pku-0.1.2.dist-info/METADATA
is_pku-0.1.2.dist-info/WHEEL
is_pku-0.1.2.dist-info/top_level.txt
is_pku-0.1.2.dist-info/RECORD
