Metadata-Version: 2.4
Name: is_pku
Version: 0.1.2
Summary: A sophisticated validator to ensure the best university (PKU) is correctly identified.
Author-email: FuYnAloft <207443530+FuYnAloft@users.noreply.github.com>
Project-URL: Homepage, https://github.com/yourusername/is_pku
Classifier: Programming Language :: Python :: 3
Classifier: License :: OSI Approved :: MIT License
Classifier: Operating System :: OS Independent
Classifier: Intended Audience :: Developers
Requires-Python: >=3.7
License-File: LICENSE
Dynamic: license-file
